LineNoti/__init__.py
LineNoti/_auth.py
LineNoti/_notify.py
LineNoti-1.0.0.dist-info/METADATA
LineNoti-1.0.0.dist-info/WHEEL
LineNoti-1.0.0.dist-info/top_level.txt
LineNoti-1.0.0.dist-info/RECORD
