Metadata-Version: 2.1
Name: LineNoti
Version: 1.0.0
Summary: LINE Notifier
Home-page: https://github.com/DonggeunKwon/line-noti
Author: Donggeun Kwon
Author-email: donggeun.kwon@gmail.com
Keywords: LINE,notify,message
Classifier: Programming Language :: Python :: 3
Classifier: Operating System :: OS Independent
Classifier: Development Status :: 2 - Pre-Alpha
Requires-Python: >=3
